{
"meta":{"test_sets":[],"test_metrics":[],"learn_metrics":[{"best_value":"Min","name":"RMSE"}],"launch_mode":"Train","parameters":"","iteration_count":190,"learn_sets":["learn"],"name":"experiment"},
"iterations":[
{"learn":[19.8316147],"iteration":0,"passed_time":0.000855353242,"remaining_time":0.1616617627},
{"learn":[19.17168202],"iteration":1,"passed_time":0.002136347844,"remaining_time":0.2008166973},
{"learn":[18.4748773],"iteration":2,"passed_time":0.003216683177,"remaining_time":0.2005065847},
{"learn":[17.93238768],"iteration":3,"passed_time":0.00393413718,"remaining_time":0.1829373789},
{"learn":[17.43024963],"iteration":4,"passed_time":0.004978682839,"remaining_time":0.184211265},
{"learn":[16.86318843],"iteration":5,"passed_time":0.006025463073,"remaining_time":0.1847808676},
{"learn":[16.36902417],"iteration":6,"passed_time":0.007417378308,"remaining_time":0.1939114615},
{"learn":[15.90212253],"iteration":7,"passed_time":0.00849423672,"remaining_time":0.1932438854},
{"learn":[15.44581251],"iteration":8,"passed_time":0.009586400188,"remaining_time":0.1927931593},
{"learn":[14.93733886],"iteration":9,"passed_time":0.01064523002,"remaining_time":0.1916141403},
{"learn":[14.46909183],"iteration":10,"passed_time":0.01175669004,"remaining_time":0.1913134106},
{"learn":[14.03111673],"iteration":11,"passed_time":0.01286825948,"remaining_time":0.1908791823},
{"learn":[13.71470361],"iteration":12,"passed_time":0.01392653088,"remaining_time":0.1896150743},
{"learn":[13.29842847],"iteration":13,"passed_time":0.01500959452,"remaining_time":0.1886920454},
{"learn":[12.97233672],"iteration":14,"passed_time":0.0161686489,"remaining_time":0.1886342371},
{"learn":[12.62937478],"iteration":15,"passed_time":0.01707309591,"remaining_time":0.1856699181},
{"learn":[12.35040565],"iteration":16,"passed_time":0.01828851621,"remaining_time":0.1861125473},
{"learn":[12.01685297],"iteration":17,"passed_time":0.01943650149,"remaining_time":0.1857265698},
{"learn":[11.67768036],"iteration":18,"passed_time":0.02054103546,"remaining_time":0.1848693191},
{"learn":[11.44967581],"iteration":19,"passed_time":0.02168637104,"remaining_time":0.1843341538},
{"learn":[11.17601682],"iteration":20,"passed_time":0.02313838358,"remaining_time":0.1862088964},
{"learn":[10.89517922],"iteration":21,"passed_time":0.02423515124,"remaining_time":0.1850684277},
{"learn":[10.67948857],"iteration":22,"passed_time":0.02534937126,"remaining_time":0.1840584783},
{"learn":[10.43288644],"iteration":23,"passed_time":0.02647247052,"remaining_time":0.1831012544},
{"learn":[10.27599135],"iteration":24,"passed_time":0.02763488284,"remaining_time":0.1823902267},
{"learn":[10.16534605],"iteration":25,"passed_time":0.02837356053,"remaining_time":0.1789716895},
{"learn":[9.993580374],"iteration":26,"passed_time":0.02948868723,"remaining_time":0.178024297},
{"learn":[9.863097483],"iteration":27,"passed_time":0.03065081469,"remaining_time":0.1773368564},
{"learn":[9.68378242],"iteration":28,"passed_time":0.03179520885,"remaining_time":0.1765182285},
{"learn":[9.482256828],"iteration":29,"passed_time":0.03289267781,"remaining_time":0.175427615},
{"learn":[9.267821877],"iteration":30,"passed_time":0.03398892917,"remaining_time":0.1743303141},
{"learn":[9.073770208],"iteration":31,"passed_time":0.03512781028,"remaining_time":0.1734435632},
{"learn":[8.926789563],"iteration":32,"passed_time":0.03630689202,"remaining_time":0.1727327893},
{"learn":[8.764114025],"iteration":33,"passed_time":0.03750509358,"remaining_time":0.1720821941},
{"learn":[8.645373142],"iteration":34,"passed_time":0.03883802533,"remaining_time":0.1719969693},
{"learn":[8.475615586],"iteration":35,"passed_time":0.03994520987,"remaining_time":0.1708767311},
{"learn":[8.320290873],"iteration":36,"passed_time":0.04107248474,"remaining_time":0.1698402747},
{"learn":[8.220160552],"iteration":37,"passed_time":0.04221160989,"remaining_time":0.1688464395},
{"learn":[8.055886605],"iteration":38,"passed_time":0.04334782219,"remaining_time":0.1678338756},
{"learn":[7.916463012],"iteration":39,"passed_time":0.04449965219,"remaining_time":0.1668736957},
{"learn":[7.812017026],"iteration":40,"passed_time":0.04567882817,"remaining_time":0.1660035463},
{"learn":[7.657714651],"iteration":41,"passed_time":0.04687346031,"remaining_time":0.1651731459},
{"learn":[7.542420006],"iteration":42,"passed_time":0.04800828306,"remaining_time":0.1641213398},
{"learn":[7.368724371],"iteration":43,"passed_time":0.04914040356,"remaining_time":0.1630567936},
{"learn":[7.283663713],"iteration":44,"passed_time":0.05025849826,"remaining_time":0.1619440499},
{"learn":[7.181063921],"iteration":45,"passed_time":0.05137837289,"remaining_time":0.1608366456},
{"learn":[7.113310067],"iteration":46,"passed_time":0.0524938574,"remaining_time":0.1597153534},
{"learn":[6.99607702],"iteration":47,"passed_time":0.05385383984,"remaining_time":0.1593176095},
{"learn":[6.882069399],"iteration":48,"passed_time":0.05500832997,"remaining_time":0.158289276},
{"learn":[6.789897224],"iteration":49,"passed_time":0.05615314838,"remaining_time":0.1572288155},
{"learn":[6.696378696],"iteration":50,"passed_time":0.05730188793,"remaining_time":0.1561757338},
{"learn":[6.625916122],"iteration":51,"passed_time":0.05843374398,"remaining_time":0.1550741667},
{"learn":[6.547661079],"iteration":52,"passed_time":0.05953194679,"remaining_time":0.1538844662},
{"learn":[6.489672822],"iteration":53,"passed_time":0.06083402135,"remaining_time":0.1532116093},
{"learn":[6.421952056],"iteration":54,"passed_time":0.06209561823,"remaining_time":0.1524165175},
{"learn":[6.300068858],"iteration":55,"passed_time":0.06322982002,"remaining_time":0.1512999265},
{"learn":[6.196459503],"iteration":56,"passed_time":0.06436457936,"remaining_time":0.1501840185},
{"learn":[6.13319236],"iteration":57,"passed_time":0.06491893632,"remaining_time":0.1477465447},
{"learn":[6.081771654],"iteration":58,"passed_time":0.06608529497,"remaining_time":0.1467317566},
{"learn":[6.049065654],"iteration":59,"passed_time":0.0672258227,"remaining_time":0.1456559492},
{"learn":[5.985529561],"iteration":60,"passed_time":0.06833718328,"remaining_time":0.1445163384},
{"learn":[5.935755453],"iteration":61,"passed_time":0.07007845298,"remaining_time":0.1446780965},
{"learn":[5.880632108],"iteration":62,"passed_time":0.07127359839,"remaining_time":0.1436785237},
{"learn":[5.849493082],"iteration":63,"passed_time":0.07209011667,"remaining_time":0.1419274172},
{"learn":[5.801950663],"iteration":64,"passed_time":0.07338135401,"remaining_time":0.1411179885},
{"learn":[5.744774299],"iteration":65,"passed_time":0.07466904279,"remaining_time":0.1402872925},
{"learn":[5.701394176],"iteration":66,"passed_time":0.07586193625,"remaining_time":0.1392689278},
{"learn":[5.641600758],"iteration":67,"passed_time":0.07700668736,"remaining_time":0.1381590567},
{"learn":[5.589616772],"iteration":68,"passed_time":0.07812640566,"remaining_time":0.1370042766},
{"learn":[5.535620396],"iteration":69,"passed_time":0.07922236782,"remaining_time":0.1358097734},
{"learn":[5.470832113],"iteration":70,"passed_time":0.08031942338,"remaining_time":0.1346198786},
{"learn":[5.437114317],"iteration":71,"passed_time":0.08143790195,"remaining_time":0.1334676726},
{"learn":[5.399567949],"iteration":72,"passed_time":0.08256292096,"remaining_time":0.1323268733},
{"learn":[5.37103664],"iteration":73,"passed_time":0.08374092407,"remaining_time":0.1312695566},
{"learn":[5.340863342],"iteration":74,"passed_time":0.08518700625,"remaining_time":0.1306200763},
{"learn":[5.309785508],"iteration":75,"passed_time":0.08631696426,"remaining_time":0.1294754464},
{"learn":[5.275854789],"iteration":76,"passed_time":0.08741780939,"remaining_time":0.1282884735},
{"learn":[5.252119959],"iteration":77,"passed_time":0.08868021047,"remaining_time":0.1273356868},
{"learn":[5.2173295],"iteration":78,"passed_time":0.08991432851,"remaining_time":0.1263353223},
{"learn":[5.122838335],"iteration":79,"passed_time":0.09105822938,"remaining_time":0.1252050654},
{"learn":[5.091783191],"iteration":80,"passed_time":0.09215137899,"remaining_time":0.1240061767},
{"learn":[5.066859391],"iteration":81,"passed_time":0.09332154632,"remaining_time":0.1229113049},
{"learn":[4.958700288],"iteration":82,"passed_time":0.09447105143,"remaining_time":0.121787982},
{"learn":[4.939127411],"iteration":83,"passed_time":0.09561188747,"remaining_time":0.1206530961},
{"learn":[4.922207131],"iteration":84,"passed_time":0.09677941465,"remaining_time":0.1195510416},
{"learn":[4.810859491],"iteration":85,"passed_time":0.09794987552,"remaining_time":0.1184510123},
{"learn":[4.687334358],"iteration":86,"passed_time":0.0991499317,"remaining_time":0.1173844019},
{"learn":[4.655667392],"iteration":87,"passed_time":0.1007288677,"remaining_time":0.1167539149},
{"learn":[4.640495765],"iteration":88,"passed_time":0.1021500626,"remaining_time":0.1159231047},
{"learn":[4.616315431],"iteration":89,"passed_time":0.1036462716,"remaining_time":0.115162524},
{"learn":[4.595025406],"iteration":90,"passed_time":0.1048662687,"remaining_time":0.1140852814},
{"learn":[4.497124548],"iteration":91,"passed_time":0.1059659063,"remaining_time":0.1128767262},
{"learn":[4.397495208],"iteration":92,"passed_time":0.1070903373,"remaining_time":0.1116963733},
{"learn":[4.313165034],"iteration":93,"passed_time":0.108250839,"remaining_time":0.1105540483},
{"learn":[4.232036739],"iteration":94,"passed_time":0.1094483527,"remaining_time":0.1094483527},
{"learn":[4.211888516],"iteration":95,"passed_time":0.1105604046,"remaining_time":0.1082570629},
{"learn":[4.195361856],"iteration":96,"passed_time":0.1116459013,"remaining_time":0.1070419466},
{"learn":[4.177108326],"iteration":97,"passed_time":0.1127362931,"remaining_time":0.105834071},
{"learn":[4.090616381],"iteration":98,"passed_time":0.1138405986,"remaining_time":0.1046413583},
{"learn":[4.01067817],"iteration":99,"passed_time":0.1149554448,"remaining_time":0.1034599003},
{"learn":[3.932336851],"iteration":100,"passed_time":0.116390556,"remaining_time":0.1025619751},
{"learn":[3.911589092],"iteration":101,"passed_time":0.1179110549,"remaining_time":0.1017271846},
{"learn":[3.840097197],"iteration":102,"passed_time":0.1191063705,"remaining_time":0.10060441},
{"learn":[3.766548105],"iteration":103,"passed_time":0.1202531946,"remaining_time":0.09944014171},
{"learn":[3.69289607],"iteration":104,"passed_time":0.1213986587,"remaining_time":0.0982751047},
{"learn":[3.678000589],"iteration":105,"passed_time":0.1225451407,"remaining_time":0.09711124358},
{"learn":[3.663988155],"iteration":106,"passed_time":0.1236643345,"remaining_time":0.09592653981},
{"learn":[3.603847168],"iteration":107,"passed_time":0.1248098272,"remaining_time":0.09476301697},
{"learn":[3.586597837],"iteration":108,"passed_time":0.125985396,"remaining_time":0.09362217502},
{"learn":[3.509565542],"iteration":109,"passed_time":0.1271706313,"remaining_time":0.09248773186},
{"learn":[3.49593919],"iteration":110,"passed_time":0.1283106896,"remaining_time":0.09132022055},
{"learn":[3.428254464],"iteration":111,"passed_time":0.1294298586,"remaining_time":0.09013865154},
{"learn":[3.381704486],"iteration":112,"passed_time":0.1305792487,"remaining_time":0.08897878006},
{"learn":[3.332904466],"iteration":113,"passed_time":0.1330123525,"remaining_time":0.08867490166},
{"learn":[3.287433229],"iteration":114,"passed_time":0.1342525824,"remaining_time":0.08755603199},
{"learn":[3.215921462],"iteration":115,"passed_time":0.1354158137,"remaining_time":0.0863859501},
{"learn":[3.150228239],"iteration":116,"passed_time":0.1365780558,"remaining_time":0.08521536813},
{"learn":[3.140486306],"iteration":117,"passed_time":0.1377101758,"remaining_time":0.08402654797},
{"learn":[3.094200184],"iteration":118,"passed_time":0.1388536564,"remaining_time":0.08284545884},
{"learn":[3.086063189],"iteration":119,"passed_time":0.1399634281,"remaining_time":0.08164533304},
{"learn":[3.075730525],"iteration":120,"passed_time":0.1411604902,"remaining_time":0.08049647788},
{"learn":[3.067911795],"iteration":121,"passed_time":0.1422908025,"remaining_time":0.07930962765},
{"learn":[3.059868936],"iteration":122,"passed_time":0.1434111392,"remaining_time":0.07811826282},
{"learn":[3.05234887],"iteration":123,"passed_time":0.1445117225,"remaining_time":0.07691752971},
{"learn":[2.998689831],"iteration":124,"passed_time":0.1456076204,"remaining_time":0.0757159626},
{"learn":[2.952705935],"iteration":125,"passed_time":0.1467523255,"remaining_time":0.07454086373},
{"learn":[2.945070545],"iteration":126,"passed_time":0.1489094185,"remaining_time":0.07386845168},
{"learn":[2.901243958],"iteration":127,"passed_time":0.1501605898,"remaining_time":0.07273403568},
{"learn":[2.89410557],"iteration":128,"passed_time":0.1512960778,"remaining_time":0.07154310655},
{"learn":[2.865470111],"iteration":129,"passed_time":0.1524658044,"remaining_time":0.07036883278},
{"learn":[2.802678096],"iteration":130,"passed_time":0.1536109098,"remaining_time":0.06918353953},
{"learn":[2.749928469],"iteration":131,"passed_time":0.1547702004,"remaining_time":0.06800508805},
{"learn":[2.705921112],"iteration":132,"passed_time":0.155942294,"remaining_time":0.06683241171},
{"learn":[2.649466289],"iteration":133,"passed_time":0.1570998134,"remaining_time":0.06565365334},
{"learn":[2.64332673],"iteration":134,"passed_time":0.1582577652,"remaining_time":0.06447538583},
{"learn":[2.600821505],"iteration":135,"passed_time":0.1594471236,"remaining_time":0.0633098873},
{"learn":[2.564748958],"iteration":136,"passed_time":0.1605780269,"remaining_time":0.06212142647},
{"learn":[2.534053977],"iteration":137,"passed_time":0.1618492625,"remaining_time":0.06098667862},
{"learn":[2.497745319],"iteration":138,"passed_time":0.1635554043,"remaining_time":0.06000953683},
{"learn":[2.488807765],"iteration":139,"passed_time":0.1647978401,"remaining_time":0.05885637147},
{"learn":[2.45617773],"iteration":140,"passed_time":0.1659235978,"remaining_time":0.05766139213},
{"learn":[2.438383236],"iteration":141,"passed_time":0.1671801202,"remaining_time":0.05651158991},
{"learn":[2.392994976],"iteration":142,"passed_time":0.1682895019,"remaining_time":0.0553119342},
{"learn":[2.361383261],"iteration":143,"passed_time":0.1694533264,"remaining_time":0.05413092371},
{"learn":[2.353415937],"iteration":144,"passed_time":0.1705927199,"remaining_time":0.05294256824},
{"learn":[2.343673906],"iteration":145,"passed_time":0.1717810535,"remaining_time":0.05176963255},
{"learn":[2.335656905],"iteration":146,"passed_time":0.172936947,"remaining_time":0.05058699811},
{"learn":[2.328190016],"iteration":147,"passed_time":0.1740748251,"remaining_time":0.04939961252},
{"learn":[2.289798073],"iteration":148,"passed_time":0.1752072804,"remaining_time":0.04821139929},
{"learn":[2.280985115],"iteration":149,"passed_time":0.1764461954,"remaining_time":0.04705231877},
{"learn":[2.275166301],"iteration":150,"passed_time":0.17765301,"remaining_time":0.04588389},
{"learn":[2.248821046],"iteration":151,"passed_time":0.1793479073,"remaining_time":0.04483697682},
{"learn":[2.214102193],"iteration":152,"passed_time":0.180636481,"remaining_time":0.04368333201},
{"learn":[2.205867641],"iteration":153,"passed_time":0.1817349969,"remaining_time":0.04248350577},
{"learn":[2.16748227],"iteration":154,"passed_time":0.182840359,"remaining_time":0.04128653267},
{"learn":[2.161541137],"iteration":155,"passed_time":0.1839657388,"remaining_time":0.04009509693},
{"learn":[2.156129064],"iteration":156,"passed_time":0.1851315282,"remaining_time":0.03891299638},
{"learn":[2.150676695],"iteration":157,"passed_time":0.1862479624,"remaining_time":0.03772110631},
{"learn":[2.118862722],"iteration":158,"passed_time":0.1873492292,"remaining_time":0.0365272082},
{"learn":[2.087764499],"iteration":159,"passed_time":0.1884727036,"remaining_time":0.03533863193},
{"learn":[2.08309919],"iteration":160,"passed_time":0.189947817,"remaining_time":0.03421420307},
{"learn":[2.075208109],"iteration":161,"passed_time":0.1915356853,"remaining_time":0.03310493326},
{"learn":[2.05453095],"iteration":162,"passed_time":0.1928159782,"remaining_time":0.03193884301},
{"learn":[2.038508114],"iteration":163,"passed_time":0.1943572139,"remaining_time":0.03081272903},
{"learn":[2.033986959],"iteration":164,"passed_time":0.1956623754,"remaining_time":0.02964581446},
{"learn":[2.030044454],"iteration":165,"passed_time":0.1969109882,"remaining_time":0.02846905854},
{"learn":[1.997330706],"iteration":166,"passed_time":0.1981515264,"remaining_time":0.02729032999},
{"learn":[1.993754696],"iteration":167,"passed_time":0.199474572,"remaining_time":0.02612167014},
{"learn":[1.98922268],"iteration":168,"passed_time":0.2006863056,"remaining_time":0.02493735158},
{"learn":[1.964493489],"iteration":169,"passed_time":0.2018684765,"remaining_time":0.02374923253},
{"learn":[1.961004452],"iteration":170,"passed_time":0.2037447947,"remaining_time":0.02263831052},
{"learn":[1.936701487],"iteration":171,"passed_time":0.2053125053,"remaining_time":0.02148619242},
{"learn":[1.89849675],"iteration":172,"passed_time":0.2067419063,"remaining_time":0.02031567866},
{"learn":[1.895089816],"iteration":173,"passed_time":0.2080387523,"remaining_time":0.01913000021},
{"learn":[1.864370433],"iteration":174,"passed_time":0.2097609946,"remaining_time":0.01797951383},
{"learn":[1.835946949],"iteration":175,"passed_time":0.2114428583,"remaining_time":0.01681931828},
{"learn":[1.827225036],"iteration":176,"passed_time":0.2126880212,"remaining_time":0.0156211541},
{"learn":[1.814232352],"iteration":177,"passed_time":0.2139667829,"remaining_time":0.01442472694},
{"learn":[1.811155032],"iteration":178,"passed_time":0.2152244274,"remaining_time":0.01322608213},
{"learn":[1.785055905],"iteration":179,"passed_time":0.2168054795,"remaining_time":0.01204474886},
{"learn":[1.767880584],"iteration":180,"passed_time":0.2181994039,"remaining_time":0.01084969412},
{"learn":[1.762524615],"iteration":181,"passed_time":0.219086062,"remaining_time":0.009630156573},
{"learn":[1.757806992],"iteration":182,"passed_time":0.2203670306,"remaining_time":0.008429339968},
{"learn":[1.749204259],"iteration":183,"passed_time":0.2217188807,"remaining_time":0.0072299635},
{"learn":[1.725502359],"iteration":184,"passed_time":0.2229497302,"remaining_time":0.006025668384},
{"learn":[1.696889053],"iteration":185,"passed_time":0.2244132917,"remaining_time":0.004826092294},
{"learn":[1.678826327],"iteration":186,"passed_time":0.2260260638,"remaining_time":0.003626086584},
{"learn":[1.669758822],"iteration":187,"passed_time":0.2275884993,"remaining_time":0.002421154248},
{"learn":[1.66604914],"iteration":188,"passed_time":0.2288443069,"remaining_time":0.001210816439},
{"learn":[1.644330381],"iteration":189,"passed_time":0.2300313178,"remaining_time":0}
]}